setup.py
EsyPro/__init__.py
EsyPro/compile.py
EsyPro/file_version_control.py
EsyPro/path_tool.py
EsyPro/project.py
EsyPro.egg-info/PKG-INFO
EsyPro.egg-info/SOURCES.txt
EsyPro.egg-info/dependency_links.txt
EsyPro.egg-info/top_level.txt