Metadata-Version: 2.1
Name: EsyPro
Version: 39.20240723.1
Summary: a python lib for project files
Home-page: http://www.xxxxx.com/
Author: Quanfa
Author-email: quanfa@tju.edu.cn
License: MIT
